aiodownload/__init__.py
aiodownload/aiodownload.py
aiodownload/api.py
aiodownload/strategy.py
aiodownload/util.py
aiodownload-0.2.5.dist-info/DESCRIPTION.rst
aiodownload-0.2.5.dist-info/METADATA
aiodownload-0.2.5.dist-info/RECORD
aiodownload-0.2.5.dist-info/WHEEL
aiodownload-0.2.5.dist-info/metadata.json
aiodownload-0.2.5.dist-info/top_level.txt
